setup.cfg
setup.py
awesome_django_admin_locking.egg-info/PKG-INFO
awesome_django_admin_locking.egg-info/SOURCES.txt
awesome_django_admin_locking.egg-info/dependency_links.txt
awesome_django_admin_locking.egg-info/not-zip-safe
awesome_django_admin_locking.egg-info/top_level.txt
locking/__init__.py
locking/admin.py
locking/api.py
locking/models.py
locking/settings.py
locking/urls.py
locking/management/__init__.py
locking/management/commands/__init__.py
locking/management/commands/delete_expired_locks.py
locking/migrations/0001_initial.py
locking/migrations/__init__.py
locking/tests/__init__.py
locking/tests/models.py
locking/tests/settings.py
locking/tests/test_admin.py
locking/tests/test_api.py
locking/tests/test_models.py
locking/tests/urls.py
locking/tests/utils.py