Metadata-Version: 1.1
Name: awesome-django-admin-locking
Version: 1.3
Summary: Prevents users from overwriting each others changes in Django. Forked from JoshMaker for upload to pypi.
Home-page: https://github.com/ndanielsen/Awesome-Django-Admin-Locking
Author: Josh West
Author-email: UNKNOWN
License: BSD
Download-URL: https://github.com/ndanielsen/Awesome-Django-Admin-Locking/archive/1.3.tar.gz3
Keywords: Awesome,Django,admin,locking
Platform: UNKNOWN
